datalchemy/__init__.py
datalchemy/data_handler.py
datalchemy/database.py
datalchemy/generators.py
datalchemy/text.md
datalchemy-0.1.0.dist-info/LICENSE
datalchemy-0.1.0.dist-info/METADATA
datalchemy-0.1.0.dist-info/WHEEL
datalchemy-0.1.0.dist-info/RECORD
