Metadata-Version: 2.3
Name: datalchemy
Version: 0.1.0
Summary: Uma biblioteca para facilitar a geração de dados sintéticos orientados por semântica e a integração com bancos SQL.
License: CoffeeWare
Author: Bruno-Gomes-QA
Author-email: bruno.gomes.qa@gmail.com
Requires-Python: >=3.12.7,<3.13
Classifier: Development Status :: 4 - Beta
Classifier: Intended Audience :: Developers
Classifier: Intended Audience :: Science/Research
Classifier: License :: Other/Proprietary License
Classifier: Natural Language :: Portuguese
Classifier: Operating System :: OS Independent
Classifier: Programming Language :: Python :: 3
Classifier: Programming Language :: Python :: 3.10
Classifier: Programming Language :: Python :: 3.11
Classifier: Programming Language :: Python :: 3.12
Classifier: Topic :: Database
Classifier: Topic :: Scientific/Engineering :: Information Analysis
Classifier: Topic :: Software Development :: Libraries
Provides-Extra: all
Provides-Extra: mssql
Provides-Extra: mysql
Provides-Extra: oracle
Provides-Extra: postgresql
Requires-Dist: cryptography (>=44.0.0,<45.0.0)
Requires-Dist: openai (>=1.59.6,<2.0.0)
Requires-Dist: psycopg2-binary (>=2.8.0,<3.0.0) ; extra == "postgresql" or extra == "all"
Requires-Dist: pydantic (>=2.10.6,<3.0.0)
Requires-Dist: pymysql (>=1.1.1,<2.0.0) ; extra == "mysql" or extra == "all"
Requires-Dist: sdv (>=1.17.4,<2.0.0)
Requires-Dist: sqlacodegen (>=2.3.0.post1,<3.0.0)
Requires-Dist: streamlit (>=1.41.1,<2.0.0)
Requires-Dist: tiktoken (>=0.8.0,<0.9.0)
Project-URL: Bug Tracker, https://github.com/Bruno-Gomes-QA/datalchemy/issues
Project-URL: Código, https://github.com/Bruno-Gomes-QA/datalchemy
Project-URL: Documentação, https://datalchemy.readthedocs.io/en/latest/
